{
  "name": "HCZ_079",
  "cellSize": 1.5,
  "boxes": [
    { "center": { "x": -286.5, "y": -1023.81, "z": -1131 }, "size": { "x": 1.5, "y": 0.12, "z": 1.5 } },
    { "center": { "x": -291, "y": -1005.56, "z": -1128 }, "size": { "x": 1.5, "y": 0.12, "z": 1.5 } },
    { "center": { "x": -291, "y": -1005.56, "z": -1126.5 }, "size": { "x": 1.5, "y": 0.12, "z": 1.5 } },
    { "center": { "x": -300, "y": -1005.31, "z": -1132.5 }, "size": { "x": 1.5, "y": 0.12, "z": 1.5 } },
    { "center": { "x": -300, "y": -1005.31, "z": -1131 }, "size": { "x": 1.5, "y": 0.12, "z": 1.5 } },
    { "center": { "x": -300, "y": -1005.31, "z": -1129.5 }, "size": { "x": 1.5, "y": 0.12, "z": 1.5 } },
    { "center": { "x": -300, "y": -1005.31, "z": -1128 }, "size": { "x": 1.5, "y": 0.12, "z": 1.5 } },
    { "center": { "x": -300, "y": -1005.31, "z": -1126.5 }, "size": { "x": 1.5, "y": 0.12, "z": 1.5 } },
    { "center": { "x": -300, "y": -1005.31, "z": -1125 }, "size": { "x": 1.5, "y": 0.12, "z": 1.5 } },
    { "center": { "x": -300, "y": -1005.31, "z": -1123.5 }, "size": { "x": 1.5, "y": 0.12, "z": 1.5 } },
    { "center": { "x": -300, "y": -1005.31, "z": -1122 }, "size": { "x": 1.5, "y": 0.12, "z": 1.5 } },
    { "center": { "x": -300, "y": -1005.31, "z": -1120.5 }, "size": { "x": 1.5, "y": 0.12, "z": 1.5 } },
    { "center": { "x": -298.5, "y": -1005.31, "z": -1132.5 }, "size": { "x": 1.5, "y": 0.12, "z": 1.5 } },
    { "center": { "x": -298.5, "y": -1005.31, "z": -1131 }, "size": { "x": 1.5, "y": 0.12, "z": 1.5 } },
    { "center": { "x": -298.5, "y": -1005.31, "z": -1129.5 }, "size": { "x": 1.5, "y": 0.12, "z": 1.5 } },
    { "center": { "x": -298.5, "y": -1005.31, "z": -1128 }, "size": { "x": 1.5, "y": 0.12, "z": 1.5 } },
    { "center": { "x": -298.5, "y": -1005.31, "z": -1126.5 }, "size": { "x": 1.5, "y": 0.12, "z": 1.5 } },
    { "center": { "x": -298.5, "y": -1005.31, "z": -1125 }, "size": { "x": 1.5, "y": 0.12, "z": 1.5 } },
    { "center": { "x": -298.5, "y": -1005.31, "z": -1123.5 }, "size": { "x": 1.5, "y": 0.12, "z": 1.5 } },
    { "center": { "x": -298.5, "y": -1005.31, "z": -1122 }, "size": { "x": 1.5, "y": 0.12, "z": 1.5 } },
    { "center": { "x": -298.5, "y": -1005.31, "z": -1120.5 }, "size": { "x": 1.5, "y": 0.12, "z": 1.5 } },
    { "center": { "x": -297, "y": -1005.31, "z": -1132.5 }, "size": { "x": 1.5, "y": 0.12, "z": 1.5 } },
    { "center": { "x": -297, "y": -1005.31, "z": -1131 }, "size": { "x": 1.5, "y": 0.12, "z": 1.5 } },
    { "center": { "x": -297, "y": -1005.31, "z": -1129.5 }, "size": { "x": 1.5, "y": 0.12, "z": 1.5 } },
    { "center": { "x": -297, "y": -1005.31, "z": -1128 }, "size": { "x": 1.5, "y": 0.12, "z": 1.5 } },
    { "center": { "x": -297, "y": -1005.31, "z": -1126.5 }, "size": { "x": 1.5, "y": 0.12, "z": 1.5 } },
    { "center": { "x": -297, "y": -1005.31, "z": -1125 }, "size": { "x": 1.5, "y": 0.12, "z": 1.5 } },
    { "center": { "x": -297, "y": -1005.31, "z": -1123.5 }, "size": { "x": 1.5, "y": 0.12, "z": 1.5 } },
    { "center": { "x": -297, "y": -1005.31, "z": -1122 }, "size": { "x": 1.5, "y": 0.12, "z": 1.5 } },
    { "center": { "x": -297, "y": -1005.31, "z": -1120.5 }, "size": { "x": 1.5, "y": 0.12, "z": 1.5 } },
    { "center": { "x": -295.5, "y": -1005.31, "z": -1132.5 }, "size": { "x": 1.5, "y": 0.12, "z": 1.5 } },
    { "center": { "x": -295.5, "y": -1005.31, "z": -1131 }, "size": { "x": 1.5, "y": 0.12, "z": 1.5 } },
    { "center": { "x": -295.5, "y": -1005.31, "z": -1129.5 }, "size": { "x": 1.5, "y": 0.12, "z": 1.5 } },
    { "center": { "x": -295.5, "y": -1005.31, "z": -1128 }, "size": { "x": 1.5, "y": 0.12, "z": 1.5 } },
    { "center": { "x": -295.5, "y": -1005.31, "z": -1126.5 }, "size": { "x": 1.5, "y": 0.12, "z": 1.5 } },
    { "center": { "x": -295.5, "y": -1005.31, "z": -1125 }, "size": { "x": 1.5, "y": 0.12, "z": 1.5 } },
    { "center": { "x": -295.5, "y": -1005.31, "z": -1123.5 }, "size": { "x": 1.5, "y": 0.12, "z": 1.5 } },
    { "center": { "x": -295.5, "y": -1005.31, "z": -1122 }, "size": { "x": 1.5, "y": 0.12, "z": 1.5 } },
    { "center": { "x": -295.5, "y": -1005.31, "z": -1120.5 }, "size": { "x": 1.5, "y": 0.12, "z": 1.5 } },
    { "center": { "x": -294, "y": -1005.31, "z": -1132.5 }, "size": { "x": 1.5, "y": 0.12, "z": 1.5 } },
    { "center": { "x": -294, "y": -1005.31, "z": -1131 }, "size": { "x": 1.5, "y": 0.12, "z": 1.5 } },
    { "center": { "x": -294, "y": -1005.31, "z": -1129.5 }, "size": { "x": 1.5, "y": 0.12, "z": 1.5 } },
    { "center": { "x": -294, "y": -1005.31, "z": -1128 }, "size": { "x": 1.5, "y": 0.12, "z": 1.5 } },
    { "center": { "x": -294, "y": -1005.31, "z": -1126.5 }, "size": { "x": 1.5, "y": 0.12, "z": 1.5 } },
    { "center": { "x": -294, "y": -1005.31, "z": -1125 }, "size": { "x": 1.5, "y": 0.12, "z": 1.5 } },
    { "center": { "x": -294, "y": -1005.31, "z": -1123.5 }, "size": { "x": 1.5, "y": 0.12, "z": 1.5 } },
    { "center": { "x": -294, "y": -1005.31, "z": -1122 }, "size": { "x": 1.5, "y": 0.12, "z": 1.5 } },
    { "center": { "x": -294, "y": -1005.31, "z": -1120.5 }, "size": { "x": 1.5, "y": 0.12, "z": 1.5 } },
    { "center": { "x": -292.5, "y": -1005.31, "z": -1132.5 }, "size": { "x": 1.5, "y": 0.12, "z": 1.5 } },
    { "center": { "x": -292.5, "y": -1005.31, "z": -1131 }, "size": { "x": 1.5, "y": 0.12, "z": 1.5 } },
    { "center": { "x": -292.5, "y": -1005.31, "z": -1129.5 }, "size": { "x": 1.5, "y": 0.12, "z": 1.5 } },
    { "center": { "x": -292.5, "y": -1005.31, "z": -1128 }, "size": { "x": 1.5, "y": 0.12, "z": 1.5 } },
    { "center": { "x": -292.5, "y": -1005.31, "z": -1126.5 }, "size": { "x": 1.5, "y": 0.12, "z": 1.5 } },
    { "center": { "x": -292.5, "y": -1005.31, "z": -1125 }, "size": { "x": 1.5, "y": 0.12, "z": 1.5 } },
    { "center": { "x": -292.5, "y": -1005.31, "z": -1123.5 }, "size": { "x": 1.5, "y": 0.12, "z": 1.5 } },
    { "center": { "x": -292.5, "y": -1005.31, "z": -1122 }, "size": { "x": 1.5, "y": 0.12, "z": 1.5 } },
    { "center": { "x": -292.5, "y": -1005.31, "z": -1120.5 }, "size": { "x": 1.5, "y": 0.12, "z": 1.5 } },
    { "center": { "x": -291, "y": -1005.31, "z": -1128 }, "size": { "x": 1.5, "y": 0.12, "z": 1.5 } },
    { "center": { "x": -291, "y": -1005.31, "z": -1126.5 }, "size": { "x": 1.5, "y": 0.12, "z": 1.5 } },
    { "center": { "x": -291, "y": -1005.31, "z": -1125 }, "size": { "x": 1.5, "y": 0.12, "z": 1.5 } },
    { "center": { "x": -289.5, "y": -1005.31, "z": -1125 }, "size": { "x": 1.5, "y": 0.12, "z": 1.5 } },
    { "center": { "x": -286.5, "y": -1005.31, "z": -1125 }, "size": { "x": 1.5, "y": 0.12, "z": 1.5 } },
    { "center": { "x": -286.5, "y": -1005.31, "z": -1123.5 }, "size": { "x": 1.5, "y": 0.12, "z": 1.5 } },
    { "center": { "x": -285, "y": -1005.31, "z": -1125 }, "size": { "x": 1.5, "y": 0.12, "z": 1.5 } },
    { "center": { "x": -285, "y": -1005.31, "z": -1122 }, "size": { "x": 1.5, "y": 0.12, "z": 1.5 } },
    { "center": { "x": -300, "y": -1005.06, "z": -1128 }, "size": { "x": 1.5, "y": 0.12, "z": 1.5 } },
    { "center": { "x": -300, "y": -1005.06, "z": -1125 }, "size": { "x": 1.5, "y": 0.12, "z": 1.5 } },
    { "center": { "x": -300, "y": -1005.06, "z": -1120.5 }, "size": { "x": 1.5, "y": 0.12, "z": 1.5 } },
    { "center": { "x": -298.5, "y": -1005.06, "z": -1120.5 }, "size": { "x": 1.5, "y": 0.12, "z": 1.5 } },
    { "center": { "x": -297, "y": -1005.06, "z": -1132.5 }, "size": { "x": 1.5, "y": 0.12, "z": 1.5 } },
    { "center": { "x": -297, "y": -1005.06, "z": -1120.5 }, "size": { "x": 1.5, "y": 0.12, "z": 1.5 } },
    { "center": { "x": -295.5, "y": -1005.06, "z": -1120.5 }, "size": { "x": 1.5, "y": 0.12, "z": 1.5 } },
    { "center": { "x": -294, "y": -1005.06, "z": -1132.5 }, "size": { "x": 1.5, "y": 0.12, "z": 1.5 } },
    { "center": { "x": -294, "y": -1005.06, "z": -1120.5 }, "size": { "x": 1.5, "y": 0.12, "z": 1.5 } },
    { "center": { "x": -292.5, "y": -1005.06, "z": -1120.5 }, "size": { "x": 1.5, "y": 0.12, "z": 1.5 } },
    { "center": { "x": -291, "y": -1005.06, "z": -1132.5 }, "size": { "x": 1.5, "y": 0.12, "z": 1.5 } },
    { "center": { "x": -291, "y": -1005.06, "z": -1131 }, "size": { "x": 1.5, "y": 0.12, "z": 1.5 } },
    { "center": { "x": -291, "y": -1005.06, "z": -1129.5 }, "size": { "x": 1.5, "y": 0.12, "z": 1.5 } },
    { "center": { "x": -291, "y": -1005.06, "z": -1128 }, "size": { "x": 1.5, "y": 0.12, "z": 1.5 } },
    { "center": { "x": -291, "y": -1005.06, "z": -1126.5 }, "size": { "x": 1.5, "y": 0.12, "z": 1.5 } },
    { "center": { "x": -291, "y": -1005.06, "z": -1125 }, "size": { "x": 1.5, "y": 0.12, "z": 1.5 } },
    { "center": { "x": -291, "y": -1005.06, "z": -1123.5 }, "size": { "x": 1.5, "y": 0.12, "z": 1.5 } },
    { "center": { "x": -291, "y": -1005.06, "z": -1122 }, "size": { "x": 1.5, "y": 0.12, "z": 1.5 } },
    { "center": { "x": -291, "y": -1005.06, "z": -1120.5 }, "size": { "x": 1.5, "y": 0.12, "z": 1.5 } },
    { "center": { "x": -291, "y": -1004.81, "z": -1128 }, "size": { "x": 1.5, "y": 0.12, "z": 1.5 } },
    { "center": { "x": -291, "y": -1004.81, "z": -1126.5 }, "size": { "x": 1.5, "y": 0.12, "z": 1.5 } },
    { "center": { "x": -291, "y": -1004.56, "z": -1128 }, "size": { "x": 1.5, "y": 0.12, "z": 1.5 } },
    { "center": { "x": -289.5, "y": -1004.56, "z": -1126.5 }, "size": { "x": 1.5, "y": 0.12, "z": 1.5 } },
    { "center": { "x": -298.5, "y": -1004.31, "z": -1131 }, "size": { "x": 1.5, "y": 0.12, "z": 1.5 } },
    { "center": { "x": -298.5, "y": -1004.31, "z": -1129.5 }, "size": { "x": 1.5, "y": 0.12, "z": 1.5 } },
    { "center": { "x": -297, "y": -1004.31, "z": -1131 }, "size": { "x": 1.5, "y": 0.12, "z": 1.5 } },
    { "center": { "x": -297, "y": -1004.31, "z": -1129.5 }, "size": { "x": 1.5, "y": 0.12, "z": 1.5 } },
    { "center": { "x": -289.5, "y": -1004.31, "z": -1128 }, "size": { "x": 1.5, "y": 0.12, "z": 1.5 } },
    { "center": { "x": -289.5, "y": -1004.31, "z": -1126.5 }, "size": { "x": 1.5, "y": 0.12, "z": 1.5 } },
    { "center": { "x": -289.5, "y": -1004.06, "z": -1129.5 }, "size": { "x": 1.5, "y": 0.12, "z": 1.5 } },
    { "center": { "x": -289.5, "y": -1004.06, "z": -1128 }, "size": { "x": 1.5, "y": 0.12, "z": 1.5 } },
    { "center": { "x": -289.5, "y": -1004.06, "z": -1126.5 }, "size": { "x": 1.5, "y": 0.12, "z": 1.5 } },
    { "center": { "x": -298.5, "y": -1003.81, "z": -1129.5 }, "size": { "x": 1.5, "y": 0.12, "z": 1.5 } },
    { "center": { "x": -289.5, "y": -1003.81, "z": -1128 }, "size": { "x": 1.5, "y": 0.12, "z": 1.5 } },
    { "center": { "x": -289.5, "y": -1003.81, "z": -1126.5 }, "size": { "x": 1.5, "y": 0.12, "z": 1.5 } },
    { "center": { "x": -297, "y": -1003.56, "z": -1131 }, "size": { "x": 1.5, "y": 0.12, "z": 1.5 } },
    { "center": { "x": -289.5, "y": -1003.56, "z": -1128 }, "size": { "x": 1.5, "y": 0.12, "z": 1.5 } },
    { "center": { "x": -289.5, "y": -1003.56, "z": -1117.5 }, "size": { "x": 1.5, "y": 0.12, "z": 1.5 } },
    { "center": { "x": -289.5, "y": -1003.56, "z": -1114.5 }, "size": { "x": 1.5, "y": 0.12, "z": 1.5 } },
    { "center": { "x": -288, "y": -1003.56, "z": -1126.5 }, "size": { "x": 1.5, "y": 0.12, "z": 1.5 } },
    { "center": { "x": -288, "y": -1003.56, "z": -1117.5 }, "size": { "x": 1.5, "y": 0.12, "z": 1.5 } },
    { "center": { "x": -288, "y": -1003.56, "z": -1114.5 }, "size": { "x": 1.5, "y": 0.12, "z": 1.5 } },
    { "center": { "x": -291, "y": -1003.31, "z": -1125 }, "size": { "x": 1.5, "y": 0.12, "z": 1.5 } },
    { "center": { "x": -291, "y": -1003.31, "z": -1123.5 }, "size": { "x": 1.5, "y": 0.12, "z": 1.5 } },
    { "center": { "x": -291, "y": -1003.31, "z": -1122 }, "size": { "x": 1.5, "y": 0.12, "z": 1.5 } },
    { "center": { "x": -291, "y": -1003.31, "z": -1120.5 }, "size": { "x": 1.5, "y": 0.12, "z": 1.5 } },
    { "center": { "x": -291, "y": -1003.31, "z": -1119 }, "size": { "x": 1.5, "y": 0.12, "z": 1.5 } },
    { "center": { "x": -291, "y": -1003.31, "z": -1117.5 }, "size": { "x": 1.5, "y": 0.12, "z": 1.5 } },
    { "center": { "x": -291, "y": -1003.31, "z": -1116 }, "size": { "x": 1.5, "y": 0.12, "z": 1.5 } },
    { "center": { "x": -291, "y": -1003.31, "z": -1114.5 }, "size": { "x": 1.5, "y": 0.12, "z": 1.5 } },
    { "center": { "x": -289.5, "y": -1003.31, "z": -1125 }, "size": { "x": 1.5, "y": 0.12, "z": 1.5 } },
    { "center": { "x": -289.5, "y": -1003.31, "z": -1123.5 }, "size": { "x": 1.5, "y": 0.12, "z": 1.5 } },
    { "center": { "x": -289.5, "y": -1003.31, "z": -1122 }, "size": { "x": 1.5, "y": 0.12, "z": 1.5 } },
    { "center": { "x": -289.5, "y": -1003.31, "z": -1120.5 }, "size": { "x": 1.5, "y": 0.12, "z": 1.5 } },
    { "center": { "x": -289.5, "y": -1003.31, "z": -1119 }, "size": { "x": 1.5, "y": 0.12, "z": 1.5 } },
    { "center": { "x": -289.5, "y": -1003.31, "z": -1117.5 }, "size": { "x": 1.5, "y": 0.12, "z": 1.5 } },
    { "center": { "x": -289.5, "y": -1003.31, "z": -1116 }, "size": { "x": 1.5, "y": 0.12, "z": 1.5 } },
    { "center": { "x": -289.5, "y": -1003.31, "z": -1114.5 }, "size": { "x": 1.5, "y": 0.12, "z": 1.5 } },
    { "center": { "x": -288, "y": -1003.31, "z": -1129.5 }, "size": { "x": 1.5, "y": 0.12, "z": 1.5 } },
    { "center": { "x": -288, "y": -1003.31, "z": -1128 }, "size": { "x": 1.5, "y": 0.12, "z": 1.5 } },
    { "center": { "x": -288, "y": -1003.31, "z": -1126.5 }, "size": { "x": 1.5, "y": 0.12, "z": 1.5 } },
    { "center": { "x": -288, "y": -1003.31, "z": -1125 }, "size": { "x": 1.5, "y": 0.12, "z": 1.5 } },
    { "center": { "x": -288, "y": -1003.31, "z": -1123.5 }, "size": { "x": 1.5, "y": 0.12, "z": 1.5 } },
    { "center": { "x": -288, "y": -1003.31, "z": -1122 }, "size": { "x": 1.5, "y": 0.12, "z": 1.5 } },
    { "center": { "x": -288, "y": -1003.31, "z": -1120.5 }, "size": { "x": 1.5, "y": 0.12, "z": 1.5 } },
    { "center": { "x": -288, "y": -1003.31, "z": -1119 }, "size": { "x": 1.5, "y": 0.12, "z": 1.5 } },
    { "center": { "x": -288, "y": -1003.31, "z": -1117.5 }, "size": { "x": 1.5, "y": 0.12, "z": 1.5 } },
    { "center": { "x": -288, "y": -1003.31, "z": -1116 }, "size": { "x": 1.5, "y": 0.12, "z": 1.5 } },
    { "center": { "x": -288, "y": -1003.31, "z": -1114.5 }, "size": { "x": 1.5, "y": 0.12, "z": 1.5 } },
    { "center": { "x": -286.5, "y": -1003.31, "z": -1129.5 }, "size": { "x": 1.5, "y": 0.12, "z": 1.5 } },
    { "center": { "x": -286.5, "y": -1003.31, "z": -1128 }, "size": { "x": 1.5, "y": 0.12, "z": 1.5 } },
    { "center": { "x": -286.5, "y": -1003.31, "z": -1126.5 }, "size": { "x": 1.5, "y": 0.12, "z": 1.5 } },
    { "center": { "x": -286.5, "y": -1003.31, "z": -1125 }, "size": { "x": 1.5, "y": 0.12, "z": 1.5 } },
    { "center": { "x": -286.5, "y": -1003.31, "z": -1123.5 }, "size": { "x": 1.5, "y": 0.12, "z": 1.5 } },
    { "center": { "x": -286.5, "y": -1003.31, "z": -1122 }, "size": { "x": 1.5, "y": 0.12, "z": 1.5 } },
    { "center": { "x": -286.5, "y": -1003.31, "z": -1120.5 }, "size": { "x": 1.5, "y": 0.12, "z": 1.5 } },
    { "center": { "x": -286.5, "y": -1003.31, "z": -1119 }, "size": { "x": 1.5, "y": 0.12, "z": 1.5 } },
    { "center": { "x": -286.5, "y": -1003.31, "z": -1117.5 }, "size": { "x": 1.5, "y": 0.12, "z": 1.5 } },
    { "center": { "x": -286.5, "y": -1003.31, "z": -1116 }, "size": { "x": 1.5, "y": 0.12, "z": 1.5 } },
    { "center": { "x": -286.5, "y": -1003.31, "z": -1114.5 }, "size": { "x": 1.5, "y": 0.12, "z": 1.5 } },
    { "center": { "x": -285, "y": -1003.31, "z": -1129.5 }, "size": { "x": 1.5, "y": 0.12, "z": 1.5 } },
    { "center": { "x": -285, "y": -1003.31, "z": -1128 }, "size": { "x": 1.5, "y": 0.12, "z": 1.5 } },
    { "center": { "x": -285, "y": -1003.31, "z": -1126.5 }, "size": { "x": 1.5, "y": 0.12, "z": 1.5 } },
    { "center": { "x": -285, "y": -1003.31, "z": -1125 }, "size": { "x": 1.5, "y": 0.12, "z": 1.5 } },
    { "center": { "x": -285, "y": -1003.31, "z": -1123.5 }, "size": { "x": 1.5, "y": 0.12, "z": 1.5 } },
    { "center": { "x": -285, "y": -1003.31, "z": -1122 }, "size": { "x": 1.5, "y": 0.12, "z": 1.5 } },
    { "center": { "x": -285, "y": -1003.31, "z": -1120.5 }, "size": { "x": 1.5, "y": 0.12, "z": 1.5 } },
    { "center": { "x": -285, "y": -1003.31, "z": -1119 }, "size": { "x": 1.5, "y": 0.12, "z": 1.5 } },
    { "center": { "x": -285, "y": -1003.31, "z": -1117.5 }, "size": { "x": 1.5, "y": 0.12, "z": 1.5 } },
    { "center": { "x": -285, "y": -1003.31, "z": -1116 }, "size": { "x": 1.5, "y": 0.12, "z": 1.5 } },
    { "center": { "x": -285, "y": -1003.31, "z": -1114.5 }, "size": { "x": 1.5, "y": 0.12, "z": 1.5 } },
    { "center": { "x": -283.5, "y": -1003.31, "z": -1129.5 }, "size": { "x": 1.5, "y": 0.12, "z": 1.5 } },
    { "center": { "x": -283.5, "y": -1003.31, "z": -1128 }, "size": { "x": 1.5, "y": 0.12, "z": 1.5 } },
    { "center": { "x": -283.5, "y": -1003.31, "z": -1126.5 }, "size": { "x": 1.5, "y": 0.12, "z": 1.5 } },
    { "center": { "x": -283.5, "y": -1003.31, "z": -1125 }, "size": { "x": 1.5, "y": 0.12, "z": 1.5 } },
    { "center": { "x": -283.5, "y": -1003.31, "z": -1123.5 }, "size": { "x": 1.5, "y": 0.12, "z": 1.5 } },
    { "center": { "x": -283.5, "y": -1003.31, "z": -1122 }, "size": { "x": 1.5, "y": 0.12, "z": 1.5 } },
    { "center": { "x": -283.5, "y": -1003.31, "z": -1120.5 }, "size": { "x": 1.5, "y": 0.12, "z": 1.5 } },
    { "center": { "x": -283.5, "y": -1003.31, "z": -1119 }, "size": { "x": 1.5, "y": 0.12, "z": 1.5 } },
    { "center": { "x": -283.5, "y": -1003.31, "z": -1117.5 }, "size": { "x": 1.5, "y": 0.12, "z": 1.5 } },
    { "center": { "x": -283.5, "y": -1003.31, "z": -1116 }, "size": { "x": 1.5, "y": 0.12, "z": 1.5 } },
    { "center": { "x": -283.5, "y": -1003.31, "z": -1114.5 }, "size": { "x": 1.5, "y": 0.12, "z": 1.5 } },
    { "center": { "x": -282, "y": -1003.31, "z": -1129.5 }, "size": { "x": 1.5, "y": 0.12, "z": 1.5 } },
    { "center": { "x": -282, "y": -1003.31, "z": -1128 }, "size": { "x": 1.5, "y": 0.12, "z": 1.5 } },
    { "center": { "x": -282, "y": -1003.31, "z": -1126.5 }, "size": { "x": 1.5, "y": 0.12, "z": 1.5 } },
    { "center": { "x": -282, "y": -1003.31, "z": -1125 }, "size": { "x": 1.5, "y": 0.12, "z": 1.5 } },
    { "center": { "x": -282, "y": -1003.31, "z": -1123.5 }, "size": { "x": 1.5, "y": 0.12, "z": 1.5 } },
    { "center": { "x": -282, "y": -1003.31, "z": -1122 }, "size": { "x": 1.5, "y": 0.12, "z": 1.5 } },
    { "center": { "x": -282, "y": -1003.31, "z": -1120.5 }, "size": { "x": 1.5, "y": 0.12, "z": 1.5 } },
    { "center": { "x": -282, "y": -1003.31, "z": -1119 }, "size": { "x": 1.5, "y": 0.12, "z": 1.5 } },
    { "center": { "x": -282, "y": -1003.31, "z": -1117.5 }, "size": { "x": 1.5, "y": 0.12, "z": 1.5 } },
    { "center": { "x": -282, "y": -1003.31, "z": -1116 }, "size": { "x": 1.5, "y": 0.12, "z": 1.5 } },
    { "center": { "x": -282, "y": -1003.31, "z": -1114.5 }, "size": { "x": 1.5, "y": 0.12, "z": 1.5 } },
    { "center": { "x": -280.5, "y": -1003.31, "z": -1129.5 }, "size": { "x": 1.5, "y": 0.12, "z": 1.5 } },
    { "center": { "x": -280.5, "y": -1003.31, "z": -1128 }, "size": { "x": 1.5, "y": 0.12, "z": 1.5 } },
    { "center": { "x": -280.5, "y": -1003.31, "z": -1126.5 }, "size": { "x": 1.5, "y": 0.12, "z": 1.5 } },
    { "center": { "x": -280.5, "y": -1003.31, "z": -1125 }, "size": { "x": 1.5, "y": 0.12, "z": 1.5 } },
    { "center": { "x": -280.5, "y": -1003.31, "z": -1123.5 }, "size": { "x": 1.5, "y": 0.12, "z": 1.5 } },
    { "center": { "x": -280.5, "y": -1003.31, "z": -1122 }, "size": { "x": 1.5, "y": 0.12, "z": 1.5 } },
    { "center": { "x": -280.5, "y": -1003.31, "z": -1120.5 }, "size": { "x": 1.5, "y": 0.12, "z": 1.5 } },
    { "center": { "x": -280.5, "y": -1003.31, "z": -1119 }, "size": { "x": 1.5, "y": 0.12, "z": 1.5 } },
    { "center": { "x": -280.5, "y": -1003.31, "z": -1117.5 }, "size": { "x": 1.5, "y": 0.12, "z": 1.5 } },
    { "center": { "x": -280.5, "y": -1003.31, "z": -1116 }, "size": { "x": 1.5, "y": 0.12, "z": 1.5 } },
    { "center": { "x": -280.5, "y": -1003.31, "z": -1114.5 }, "size": { "x": 1.5, "y": 0.12, "z": 1.5 } },
    { "center": { "x": -279, "y": -1003.31, "z": -1129.5 }, "size": { "x": 1.5, "y": 0.12, "z": 1.5 } },
    { "center": { "x": -279, "y": -1003.31, "z": -1128 }, "size": { "x": 1.5, "y": 0.12, "z": 1.5 } },
    { "center": { "x": -279, "y": -1003.31, "z": -1126.5 }, "size": { "x": 1.5, "y": 0.12, "z": 1.5 } },
    { "center": { "x": -279, "y": -1003.31, "z": -1125 }, "size": { "x": 1.5, "y": 0.12, "z": 1.5 } },
    { "center": { "x": -279, "y": -1003.31, "z": -1123.5 }, "size": { "x": 1.5, "y": 0.12, "z": 1.5 } },
    { "center": { "x": -279, "y": -1003.31, "z": -1122 }, "size": { "x": 1.5, "y": 0.12, "z": 1.5 } },
    { "center": { "x": -279, "y": -1003.31, "z": -1120.5 }, "size": { "x": 1.5, "y": 0.12, "z": 1.5 } },
    { "center": { "x": -279, "y": -1003.31, "z": -1119 }, "size": { "x": 1.5, "y": 0.12, "z": 1.5 } },
    { "center": { "x": -279, "y": -1003.31, "z": -1117.5 }, "size": { "x": 1.5, "y": 0.12, "z": 1.5 } },
    { "center": { "x": -279, "y": -1003.31, "z": -1116 }, "size": { "x": 1.5, "y": 0.12, "z": 1.5 } },
    { "center": { "x": -279, "y": -1003.31, "z": -1114.5 }, "size": { "x": 1.5, "y": 0.12, "z": 1.5 } },
    { "center": { "x": -277.5, "y": -1003.31, "z": -1129.5 }, "size": { "x": 1.5, "y": 0.12, "z": 1.5 } },
    { "center": { "x": -277.5, "y": -1003.31, "z": -1128 }, "size": { "x": 1.5, "y": 0.12, "z": 1.5 } },
    { "center": { "x": -277.5, "y": -1003.31, "z": -1126.5 }, "size": { "x": 1.5, "y": 0.12, "z": 1.5 } },
    { "center": { "x": -277.5, "y": -1003.31, "z": -1125 }, "size": { "x": 1.5, "y": 0.12, "z": 1.5 } },
    { "center": { "x": -277.5, "y": -1003.31, "z": -1123.5 }, "size": { "x": 1.5, "y": 0.12, "z": 1.5 } },
    { "center": { "x": -277.5, "y": -1003.31, "z": -1122 }, "size": { "x": 1.5, "y": 0.12, "z": 1.5 } },
    { "center": { "x": -277.5, "y": -1003.31, "z": -1120.5 }, "size": { "x": 1.5, "y": 0.12, "z": 1.5 } },
    { "center": { "x": -277.5, "y": -1003.31, "z": -1119 }, "size": { "x": 1.5, "y": 0.12, "z": 1.5 } },
    { "center": { "x": -277.5, "y": -1003.31, "z": -1117.5 }, "size": { "x": 1.5, "y": 0.12, "z": 1.5 } },
    { "center": { "x": -277.5, "y": -1003.31, "z": -1116 }, "size": { "x": 1.5, "y": 0.12, "z": 1.5 } },
    { "center": { "x": -277.5, "y": -1003.31, "z": -1114.5 }, "size": { "x": 1.5, "y": 0.12, "z": 1.5 } },
    { "center": { "x": -289.5, "y": -1003.06, "z": -1117.5 }, "size": { "x": 1.5, "y": 0.12, "z": 1.5 } },
    { "center": { "x": -289.5, "y": -1003.06, "z": -1116 }, "size": { "x": 1.5, "y": 0.12, "z": 1.5 } },
    { "center": { "x": -288, "y": -1003.06, "z": -1122 }, "size": { "x": 1.5, "y": 0.12, "z": 1.5 } },
    { "center": { "x": -285, "y": -1003.06, "z": -1129.5 }, "size": { "x": 1.5, "y": 0.12, "z": 1.5 } },
    { "center": { "x": -285, "y": -1003.06, "z": -1125 }, "size": { "x": 1.5, "y": 0.12, "z": 1.5 } },
    { "center": { "x": -283.5, "y": -1003.06, "z": -1123.5 }, "size": { "x": 1.5, "y": 0.12, "z": 1.5 } },
    { "center": { "x": -283.5, "y": -1003.06, "z": -1122 }, "size": { "x": 1.5, "y": 0.12, "z": 1.5 } },
    { "center": { "x": -283.5, "y": -1003.06, "z": -1120.5 }, "size": { "x": 1.5, "y": 0.12, "z": 1.5 } },
    { "center": { "x": -283.5, "y": -1003.06, "z": -1119 }, "size": { "x": 1.5, "y": 0.12, "z": 1.5 } },
    { "center": { "x": -283.5, "y": -1003.06, "z": -1114.5 }, "size": { "x": 1.5, "y": 0.12, "z": 1.5 } },
    { "center": { "x": -283.5, "y": -1003.06, "z": -1113 }, "size": { "x": 1.5, "y": 0.12, "z": 1.5 } },
    { "center": { "x": -282, "y": -1003.06, "z": -1123.5 }, "size": { "x": 1.5, "y": 0.12, "z": 1.5 } },
    { "center": { "x": -279, "y": -1003.06, "z": -1129.5 }, "size": { "x": 1.5, "y": 0.12, "z": 1.5 } },
    { "center": { "x": -279, "y": -1003.06, "z": -1128 }, "size": { "x": 1.5, "y": 0.12, "z": 1.5 } },
    { "center": { "x": -279, "y": -1003.06, "z": -1126.5 }, "size": { "x": 1.5, "y": 0.12, "z": 1.5 } },
    { "center": { "x": -279, "y": -1003.06, "z": -1125 }, "size": { "x": 1.5, "y": 0.12, "z": 1.5 } },
    { "center": { "x": -279, "y": -1003.06, "z": -1123.5 }, "size": { "x": 1.5, "y": 0.12, "z": 1.5 } },
    { "center": { "x": -279, "y": -1003.06, "z": -1122 }, "size": { "x": 1.5, "y": 0.12, "z": 1.5 } },
    { "center": { "x": -279, "y": -1003.06, "z": -1119 }, "size": { "x": 1.5, "y": 0.12, "z": 1.5 } },
    { "center": { "x": -279, "y": -1003.06, "z": -1117.5 }, "size": { "x": 1.5, "y": 0.12, "z": 1.5 } },
    { "center": { "x": -279, "y": -1003.06, "z": -1116 }, "size": { "x": 1.5, "y": 0.12, "z": 1.5 } },
    { "center": { "x": -279, "y": -1003.06, "z": -1114.5 }, "size": { "x": 1.5, "y": 0.12, "z": 1.5 } },
    { "center": { "x": -291, "y": -1002.81, "z": -1123.5 }, "size": { "x": 1.5, "y": 0.12, "z": 1.5 } },
    { "center": { "x": -291, "y": -1002.81, "z": -1122 }, "size": { "x": 1.5, "y": 0.12, "z": 1.5 } },
    { "center": { "x": -289.5, "y": -1002.81, "z": -1117.5 }, "size": { "x": 1.5, "y": 0.12, "z": 1.5 } },
    { "center": { "x": -289.5, "y": -1002.81, "z": -1116 }, "size": { "x": 1.5, "y": 0.12, "z": 1.5 } },
    { "center": { "x": -288, "y": -1002.81, "z": -1122 }, "size": { "x": 1.5, "y": 0.12, "z": 1.5 } },
    { "center": { "x": -288, "y": -1002.81, "z": -1120.5 }, "size": { "x": 1.5, "y": 0.12, "z": 1.5 } },
    { "center": { "x": -286.5, "y": -1002.81, "z": -1122 }, "size": { "x": 1.5, "y": 0.12, "z": 1.5 } },
    { "center": { "x": -286.5, "y": -1002.81, "z": -1120.5 }, "size": { "x": 1.5, "y": 0.12, "z": 1.5 } },
    { "center": { "x": -283.5, "y": -1002.81, "z": -1123.5 }, "size": { "x": 1.5, "y": 0.12, "z": 1.5 } },
    { "center": { "x": -283.5, "y": -1002.81, "z": -1122 }, "size": { "x": 1.5, "y": 0.12, "z": 1.5 } },
    { "center": { "x": -282, "y": -1002.81, "z": -1129.5 }, "size": { "x": 1.5, "y": 0.12, "z": 1.5 } },
    { "center": { "x": -282, "y": -1002.81, "z": -1123.5 }, "size": { "x": 1.5, "y": 0.12, "z": 1.5 } },
    { "center": { "x": -279, "y": -1002.81, "z": -1129.5 }, "size": { "x": 1.5, "y": 0.12, "z": 1.5 } },
    { "center": { "x": -279, "y": -1002.81, "z": -1128 }, "size": { "x": 1.5, "y": 0.12, "z": 1.5 } },
    { "center": { "x": -279, "y": -1002.81, "z": -1126.5 }, "size": { "x": 1.5, "y": 0.12, "z": 1.5 } },
    { "center": { "x": -279, "y": -1002.81, "z": -1123.5 }, "size": { "x": 1.5, "y": 0.12, "z": 1.5 } },
    { "center": { "x": -279, "y": -1002.81, "z": -1122 }, "size": { "x": 1.5, "y": 0.12, "z": 1.5 } },
    { "center": { "x": -279, "y": -1002.81, "z": -1117.5 }, "size": { "x": 1.5, "y": 0.12, "z": 1.5 } },
    { "center": { "x": -279, "y": -1002.81, "z": -1116 }, "size": { "x": 1.5, "y": 0.12, "z": 1.5 } },
    { "center": { "x": -277.5, "y": -1002.81, "z": -1128 }, "size": { "x": 1.5, "y": 0.12, "z": 1.5 } },
    { "center": { "x": -277.5, "y": -1002.81, "z": -1126.5 }, "size": { "x": 1.5, "y": 0.12, "z": 1.5 } },
    { "center": { "x": -277.5, "y": -1002.81, "z": -1123.5 }, "size": { "x": 1.5, "y": 0.12, "z": 1.5 } },
    { "center": { "x": -277.5, "y": -1002.81, "z": -1122 }, "size": { "x": 1.5, "y": 0.12, "z": 1.5 } },
    { "center": { "x": -277.5, "y": -1002.81, "z": -1117.5 }, "size": { "x": 1.5, "y": 0.12, "z": 1.5 } },
    { "center": { "x": -277.5, "y": -1002.81, "z": -1116 }, "size": { "x": 1.5, "y": 0.12, "z": 1.5 } },
    { "center": { "x": -289.5, "y": -1002.56, "z": -1117.5 }, "size": { "x": 1.5, "y": 0.12, "z": 1.5 } },
    { "center": { "x": -289.5, "y": -1002.56, "z": -1116 }, "size": { "x": 1.5, "y": 0.12, "z": 1.5 } },
    { "center": { "x": -288, "y": -1002.56, "z": -1122 }, "size": { "x": 1.5, "y": 0.12, "z": 1.5 } },
    { "center": { "x": -288, "y": -1002.56, "z": -1120.5 }, "size": { "x": 1.5, "y": 0.12, "z": 1.5 } },
    { "center": { "x": -286.5, "y": -1002.56, "z": -1131 }, "size": { "x": 1.5, "y": 0.12, "z": 1.5 } },
    { "center": { "x": -286.5, "y": -1002.56, "z": -1129.5 }, "size": { "x": 1.5, "y": 0.12, "z": 1.5 } },
    { "center": { "x": -286.5, "y": -1002.56, "z": -1125 }, "size": { "x": 1.5, "y": 0.12, "z": 1.5 } },
    { "center": { "x": -286.5, "y": -1002.56, "z": -1123.5 }, "size": { "x": 1.5, "y": 0.12, "z": 1.5 } },
    { "center": { "x": -286.5, "y": -1002.56, "z": -1122 }, "size": { "x": 1.5, "y": 0.12, "z": 1.5 } },
    { "center": { "x": -286.5, "y": -1002.56, "z": -1120.5 }, "size": { "x": 1.5, "y": 0.12, "z": 1.5 } },
    { "center": { "x": -285, "y": -1002.56, "z": -1131 }, "size": { "x": 1.5, "y": 0.12, "z": 1.5 } },
    { "center": { "x": -285, "y": -1002.56, "z": -1129.5 }, "size": { "x": 1.5, "y": 0.12, "z": 1.5 } },
    { "center": { "x": -285, "y": -1002.56, "z": -1125 }, "size": { "x": 1.5, "y": 0.12, "z": 1.5 } },
    { "center": { "x": -285, "y": -1002.56, "z": -1123.5 }, "size": { "x": 1.5, "y": 0.12, "z": 1.5 } },
    { "center": { "x": -285, "y": -1002.56, "z": -1119 }, "size": { "x": 1.5, "y": 0.12, "z": 1.5 } },
    { "center": { "x": -285, "y": -1002.56, "z": -1113 }, "size": { "x": 1.5, "y": 0.12, "z": 1.5 } },
    { "center": { "x": -283.5, "y": -1002.56, "z": -1123.5 }, "size": { "x": 1.5, "y": 0.12, "z": 1.5 } },
    { "center": { "x": -283.5, "y": -1002.56, "z": -1119 }, "size": { "x": 1.5, "y": 0.12, "z": 1.5 } },
    { "center": { "x": -283.5, "y": -1002.56, "z": -1113 }, "size": { "x": 1.5, "y": 0.12, "z": 1.5 } },
    { "center": { "x": -282, "y": -1002.56, "z": -1129.5 }, "size": { "x": 1.5, "y": 0.12, "z": 1.5 } },
    { "center": { "x": -282, "y": -1002.56, "z": -1123.5 }, "size": { "x": 1.5, "y": 0.12, "z": 1.5 } },
    { "center": { "x": -280.5, "y": -1002.56, "z": -1129.5 }, "size": { "x": 1.5, "y": 0.12, "z": 1.5 } },
    { "center": { "x": -280.5, "y": -1002.56, "z": -1128 }, "size": { "x": 1.5, "y": 0.12, "z": 1.5 } },
    { "center": { "x": -279, "y": -1002.56, "z": -1129.5 }, "size": { "x": 1.5, "y": 0.12, "z": 1.5 } },
    { "center": { "x": -279, "y": -1002.56, "z": -1125 }, "size": { "x": 1.5, "y": 0.12, "z": 1.5 } },
    { "center": { "x": -279, "y": -1002.56, "z": -1120.5 }, "size": { "x": 1.5, "y": 0.12, "z": 1.5 } },
    { "center": { "x": -279, "y": -1002.56, "z": -1114.5 }, "size": { "x": 1.5, "y": 0.12, "z": 1.5 } },
    { "center": { "x": -288, "y": -1002.31, "z": -1125 }, "size": { "x": 1.5, "y": 0.12, "z": 1.5 } },
    { "center": { "x": -288, "y": -1002.31, "z": -1120.5 }, "size": { "x": 1.5, "y": 0.12, "z": 1.5 } },
    { "center": { "x": -286.5, "y": -1002.31, "z": -1125 }, "size": { "x": 1.5, "y": 0.12, "z": 1.5 } },
    { "center": { "x": -286.5, "y": -1002.31, "z": -1120.5 }, "size": { "x": 1.5, "y": 0.12, "z": 1.5 } },
    { "center": { "x": -282, "y": -1002.31, "z": -1129.5 }, "size": { "x": 1.5, "y": 0.12, "z": 1.5 } },
    { "center": { "x": -279, "y": -1002.31, "z": -1129.5 }, "size": { "x": 1.5, "y": 0.12, "z": 1.5 } },
    { "center": { "x": -291, "y": -1002.06, "z": -1125 }, "size": { "x": 1.5, "y": 0.12, "z": 1.5 } },
    { "center": { "x": -291, "y": -1002.06, "z": -1120.5 }, "size": { "x": 1.5, "y": 0.12, "z": 1.5 } },
    { "center": { "x": -289.5, "y": -1002.06, "z": -1125 }, "size": { "x": 1.5, "y": 0.12, "z": 1.5 } },
    { "center": { "x": -289.5, "y": -1002.06, "z": -1120.5 }, "size": { "x": 1.5, "y": 0.12, "z": 1.5 } },
    { "center": { "x": -288, "y": -1002.06, "z": -1125 }, "size": { "x": 1.5, "y": 0.12, "z": 1.5 } },
    { "center": { "x": -291, "y": -1001.81, "z": -1125 }, "size": { "x": 1.5, "y": 0.12, "z": 1.5 } },
    { "center": { "x": -291, "y": -1001.81, "z": -1116 }, "size": { "x": 1.5, "y": 0.12, "z": 1.5 } },
    { "center": { "x": -289.5, "y": -1001.81, "z": -1120.5 }, "size": { "x": 1.5, "y": 0.12, "z": 1.5 } },
    { "center": { "x": -286.5, "y": -1001.81, "z": -1123.5 }, "size": { "x": 1.5, "y": 0.12, "z": 1.5 } },
    { "center": { "x": -283.5, "y": -1001.81, "z": -1122 }, "size": { "x": 1.5, "y": 0.12, "z": 1.5 } },
    { "center": { "x": -291, "y": -1001.56, "z": -1125 }, "size": { "x": 1.5, "y": 0.12, "z": 1.5 } },
    { "center": { "x": -291, "y": -1001.56, "z": -1120.5 }, "size": { "x": 1.5, "y": 0.12, "z": 1.5 } },
    { "center": { "x": -289.5, "y": -1001.56, "z": -1125 }, "size": { "x": 1.5, "y": 0.12, "z": 1.5 } },
    { "center": { "x": -289.5, "y": -1001.56, "z": -1120.5 }, "size": { "x": 1.5, "y": 0.12, "z": 1.5 } },
    { "center": { "x": -288, "y": -1001.56, "z": -1125 }, "size": { "x": 1.5, "y": 0.12, "z": 1.5 } },
    { "center": { "x": -288, "y": -1001.56, "z": -1120.5 }, "size": { "x": 1.5, "y": 0.12, "z": 1.5 } },
    { "center": { "x": -286.5, "y": -1001.56, "z": -1120.5 }, "size": { "x": 1.5, "y": 0.12, "z": 1.5 } },
    { "center": { "x": -283.5, "y": -1001.56, "z": -1122 }, "size": { "x": 1.5, "y": 0.12, "z": 1.5 } },
    { "center": { "x": -288, "y": -1001.06, "z": -1125 }, "size": { "x": 1.5, "y": 0.12, "z": 1.5 } },
    { "center": { "x": -291, "y": -1000.81, "z": -1123.5 }, "size": { "x": 1.5, "y": 0.12, "z": 1.5 } },
    { "center": { "x": -285, "y": -1000.81, "z": -1129.5 }, "size": { "x": 1.5, "y": 0.12, "z": 1.5 } },
    { "center": { "x": -285, "y": -1000.81, "z": -1128 }, "size": { "x": 1.5, "y": 0.12, "z": 1.5 } },
    { "center": { "x": -285, "y": -1000.81, "z": -1126.5 }, "size": { "x": 1.5, "y": 0.12, "z": 1.5 } },
    { "center": { "x": -285, "y": -1000.81, "z": -1125 }, "size": { "x": 1.5, "y": 0.12, "z": 1.5 } },
    { "center": { "x": -283.5, "y": -1000.81, "z": -1117.5 }, "size": { "x": 1.5, "y": 0.12, "z": 1.5 } },
    { "center": { "x": -283.5, "y": -1000.81, "z": -1116 }, "size": { "x": 1.5, "y": 0.12, "z": 1.5 } },
    { "center": { "x": -283.5, "y": -1000.81, "z": -1114.5 }, "size": { "x": 1.5, "y": 0.12, "z": 1.5 } },
    { "center": { "x": -280.5, "y": -1000.81, "z": -1129.5 }, "size": { "x": 1.5, "y": 0.12, "z": 1.5 } },
    { "center": { "x": -298.5, "y": -999.56, "z": -1119 }, "size": { "x": 1.5, "y": 0.12, "z": 1.5 } },
    { "center": { "x": -297, "y": -999.56, "z": -1114.5 }, "size": { "x": 1.5, "y": 0.12, "z": 1.5 } },
    { "center": { "x": -294, "y": -999.56, "z": -1119 }, "size": { "x": 1.5, "y": 0.12, "z": 1.5 } },
    { "center": { "x": -292.5, "y": -999.56, "z": -1114.5 }, "size": { "x": 1.5, "y": 0.12, "z": 1.5 } },
    { "center": { "x": -300, "y": -998.81, "z": -1132.5 }, "size": { "x": 1.5, "y": 0.12, "z": 1.5 } },
    { "center": { "x": -300, "y": -998.81, "z": -1131 }, "size": { "x": 1.5, "y": 0.12, "z": 1.5 } },
    { "center": { "x": -300, "y": -998.81, "z": -1129.5 }, "size": { "x": 1.5, "y": 0.12, "z": 1.5 } },
    { "center": { "x": -300, "y": -998.81, "z": -1128 }, "size": { "x": 1.5, "y": 0.12, "z": 1.5 } },
    { "center": { "x": -300, "y": -998.81, "z": -1126.5 }, "size": { "x": 1.5, "y": 0.12, "z": 1.5 } },
    { "center": { "x": -300, "y": -998.81, "z": -1125 }, "size": { "x": 1.5, "y": 0.12, "z": 1.5 } },
    { "center": { "x": -300, "y": -998.81, "z": -1123.5 }, "size": { "x": 1.5, "y": 0.12, "z": 1.5 } },
    { "center": { "x": -300, "y": -998.81, "z": -1122 }, "size": { "x": 1.5, "y": 0.12, "z": 1.5 } },
    { "center": { "x": -300, "y": -998.81, "z": -1120.5 }, "size": { "x": 1.5, "y": 0.12, "z": 1.5 } },
    { "center": { "x": -298.5, "y": -998.81, "z": -1132.5 }, "size": { "x": 1.5, "y": 0.12, "z": 1.5 } },
    { "center": { "x": -298.5, "y": -998.81, "z": -1131 }, "size": { "x": 1.5, "y": 0.12, "z": 1.5 } },
    { "center": { "x": -298.5, "y": -998.81, "z": -1129.5 }, "size": { "x": 1.5, "y": 0.12, "z": 1.5 } },
    { "center": { "x": -298.5, "y": -998.81, "z": -1128 }, "size": { "x": 1.5, "y": 0.12, "z": 1.5 } },
    { "center": { "x": -298.5, "y": -998.81, "z": -1126.5 }, "size": { "x": 1.5, "y": 0.12, "z": 1.5 } },
    { "center": { "x": -298.5, "y": -998.81, "z": -1125 }, "size": { "x": 1.5, "y": 0.12, "z": 1.5 } },
    { "center": { "x": -298.5, "y": -998.81, "z": -1123.5 }, "size": { "x": 1.5, "y": 0.12, "z": 1.5 } },
    { "center": { "x": -298.5, "y": -998.81, "z": -1122 }, "size": { "x": 1.5, "y": 0.12, "z": 1.5 } },
    { "center": { "x": -298.5, "y": -998.81, "z": -1120.5 }, "size": { "x": 1.5, "y": 0.12, "z": 1.5 } },
    { "center": { "x": -298.5, "y": -998.81, "z": -1119 }, "size": { "x": 1.5, "y": 0.12, "z": 1.5 } },
    { "center": { "x": -297, "y": -998.81, "z": -1132.5 }, "size": { "x": 1.5, "y": 0.12, "z": 1.5 } },
    { "center": { "x": -297, "y": -998.81, "z": -1131 }, "size": { "x": 1.5, "y": 0.12, "z": 1.5 } },
    { "center": { "x": -297, "y": -998.81, "z": -1129.5 }, "size": { "x": 1.5, "y": 0.12, "z": 1.5 } },
    { "center": { "x": -297, "y": -998.81, "z": -1128 }, "size": { "x": 1.5, "y": 0.12, "z": 1.5 } },
    { "center": { "x": -297, "y": -998.81, "z": -1126.5 }, "size": { "x": 1.5, "y": 0.12, "z": 1.5 } },
    { "center": { "x": -297, "y": -998.81, "z": -1125 }, "size": { "x": 1.5, "y": 0.12, "z": 1.5 } },
    { "center": { "x": -297, "y": -998.81, "z": -1123.5 }, "size": { "x": 1.5, "y": 0.12, "z": 1.5 } },
    { "center": { "x": -297, "y": -998.81, "z": -1122 }, "size": { "x": 1.5, "y": 0.12, "z": 1.5 } },
    { "center": { "x": -297, "y": -998.81, "z": -1120.5 }, "size": { "x": 1.5, "y": 0.12, "z": 1.5 } },
    { "center": { "x": -297, "y": -998.81, "z": -1114.5 }, "size": { "x": 1.5, "y": 0.12, "z": 1.5 } },
    { "center": { "x": -295.5, "y": -998.81, "z": -1132.5 }, "size": { "x": 1.5, "y": 0.12, "z": 1.5 } },
    { "center": { "x": -295.5, "y": -998.81, "z": -1131 }, "size": { "x": 1.5, "y": 0.12, "z": 1.5 } },
    { "center": { "x": -295.5, "y": -998.81, "z": -1129.5 }, "size": { "x": 1.5, "y": 0.12, "z": 1.5 } },
    { "center": { "x": -295.5, "y": -998.81, "z": -1128 }, "size": { "x": 1.5, "y": 0.12, "z": 1.5 } },
    { "center": { "x": -295.5, "y": -998.81, "z": -1126.5 }, "size": { "x": 1.5, "y": 0.12, "z": 1.5 } },
    { "center": { "x": -295.5, "y": -998.81, "z": -1125 }, "size": { "x": 1.5, "y": 0.12, "z": 1.5 } },
    { "center": { "x": -295.5, "y": -998.81, "z": -1123.5 }, "size": { "x": 1.5, "y": 0.12, "z": 1.5 } },
    { "center": { "x": -295.5, "y": -998.81, "z": -1122 }, "size": { "x": 1.5, "y": 0.12, "z": 1.5 } },
    { "center": { "x": -295.5, "y": -998.81, "z": -1120.5 }, "size": { "x": 1.5, "y": 0.12, "z": 1.5 } },
    { "center": { "x": -294, "y": -998.81, "z": -1132.5 }, "size": { "x": 1.5, "y": 0.12, "z": 1.5 } },
    { "center": { "x": -294, "y": -998.81, "z": -1131 }, "size": { "x": 1.5, "y": 0.12, "z": 1.5 } },
    { "center": { "x": -294, "y": -998.81, "z": -1129.5 }, "size": { "x": 1.5, "y": 0.12, "z": 1.5 } },
    { "center": { "x": -294, "y": -998.81, "z": -1128 }, "size": { "x": 1.5, "y": 0.12, "z": 1.5 } },
    { "center": { "x": -294, "y": -998.81, "z": -1126.5 }, "size": { "x": 1.5, "y": 0.12, "z": 1.5 } },
    { "center": { "x": -294, "y": -998.81, "z": -1125 }, "size": { "x": 1.5, "y": 0.12, "z": 1.5 } },
    { "center": { "x": -294, "y": -998.81, "z": -1123.5 }, "size": { "x": 1.5, "y": 0.12, "z": 1.5 } },
    { "center": { "x": -294, "y": -998.81, "z": -1122 }, "size": { "x": 1.5, "y": 0.12, "z": 1.5 } },
    { "center": { "x": -294, "y": -998.81, "z": -1120.5 }, "size": { "x": 1.5, "y": 0.12, "z": 1.5 } },
    { "center": { "x": -294, "y": -998.81, "z": -1119 }, "size": { "x": 1.5, "y": 0.12, "z": 1.5 } },
    { "center": { "x": -292.5, "y": -998.81, "z": -1132.5 }, "size": { "x": 1.5, "y": 0.12, "z": 1.5 } },
    { "center": { "x": -292.5, "y": -998.81, "z": -1131 }, "size": { "x": 1.5, "y": 0.12, "z": 1.5 } },
    { "center": { "x": -292.5, "y": -998.81, "z": -1129.5 }, "size": { "x": 1.5, "y": 0.12, "z": 1.5 } },
    { "center": { "x": -292.5, "y": -998.81, "z": -1128 }, "size": { "x": 1.5, "y": 0.12, "z": 1.5 } },
    { "center": { "x": -292.5, "y": -998.81, "z": -1126.5 }, "size": { "x": 1.5, "y": 0.12, "z": 1.5 } },
    { "center": { "x": -292.5, "y": -998.81, "z": -1125 }, "size": { "x": 1.5, "y": 0.12, "z": 1.5 } },
    { "center": { "x": -292.5, "y": -998.81, "z": -1123.5 }, "size": { "x": 1.5, "y": 0.12, "z": 1.5 } },
    { "center": { "x": -292.5, "y": -998.81, "z": -1122 }, "size": { "x": 1.5, "y": 0.12, "z": 1.5 } },
    { "center": { "x": -292.5, "y": -998.81, "z": -1120.5 }, "size": { "x": 1.5, "y": 0.12, "z": 1.5 } },
    { "center": { "x": -292.5, "y": -998.81, "z": -1114.5 }, "size": { "x": 1.5, "y": 0.12, "z": 1.5 } },
    { "center": { "x": -298.5, "y": -998.06, "z": -1119 }, "size": { "x": 1.5, "y": 0.12, "z": 1.5 } },
    { "center": { "x": -297, "y": -998.06, "z": -1114.5 }, "size": { "x": 1.5, "y": 0.12, "z": 1.5 } },
    { "center": { "x": -294, "y": -998.06, "z": -1119 }, "size": { "x": 1.5, "y": 0.12, "z": 1.5 } },
    { "center": { "x": -292.5, "y": -998.06, "z": -1114.5 }, "size": { "x": 1.5, "y": 0.12, "z": 1.5 } },
    { "center": { "x": -298.5, "y": -997.31, "z": -1119 }, "size": { "x": 1.5, "y": 0.12, "z": 1.5 } },
    { "center": { "x": -297, "y": -997.31, "z": -1114.5 }, "size": { "x": 1.5, "y": 0.12, "z": 1.5 } },
    { "center": { "x": -294, "y": -997.31, "z": -1119 }, "size": { "x": 1.5, "y": 0.12, "z": 1.5 } },
    { "center": { "x": -292.5, "y": -997.31, "z": -1114.5 }, "size": { "x": 1.5, "y": 0.12, "z": 1.5 } },
    { "center": { "x": -300, "y": -994.31, "z": -1117.5 }, "size": { "x": 1.5, "y": 0.12, "z": 1.5 } },
    { "center": { "x": -300, "y": -994.31, "z": -1116 }, "size": { "x": 1.5, "y": 0.12, "z": 1.5 } },
    { "center": { "x": -300, "y": -994.31, "z": -1114.5 }, "size": { "x": 1.5, "y": 0.12, "z": 1.5 } },
    { "center": { "x": -298.5, "y": -994.31, "z": -1117.5 }, "size": { "x": 1.5, "y": 0.12, "z": 1.5 } },
    { "center": { "x": -298.5, "y": -994.31, "z": -1116 }, "size": { "x": 1.5, "y": 0.12, "z": 1.5 } },
    { "center": { "x": -298.5, "y": -994.31, "z": -1114.5 }, "size": { "x": 1.5, "y": 0.12, "z": 1.5 } },
    { "center": { "x": -297, "y": -994.31, "z": -1117.5 }, "size": { "x": 1.5, "y": 0.12, "z": 1.5 } },
    { "center": { "x": -297, "y": -994.31, "z": -1116 }, "size": { "x": 1.5, "y": 0.12, "z": 1.5 } },
    { "center": { "x": -297, "y": -994.31, "z": -1114.5 }, "size": { "x": 1.5, "y": 0.12, "z": 1.5 } },
    { "center": { "x": -295.5, "y": -994.31, "z": -1117.5 }, "size": { "x": 1.5, "y": 0.12, "z": 1.5 } },
    { "center": { "x": -295.5, "y": -994.31, "z": -1116 }, "size": { "x": 1.5, "y": 0.12, "z": 1.5 } },
    { "center": { "x": -295.5, "y": -994.31, "z": -1114.5 }, "size": { "x": 1.5, "y": 0.12, "z": 1.5 } },
    { "center": { "x": -294, "y": -994.31, "z": -1117.5 }, "size": { "x": 1.5, "y": 0.12, "z": 1.5 } },
    { "center": { "x": -294, "y": -994.31, "z": -1116 }, "size": { "x": 1.5, "y": 0.12, "z": 1.5 } },
    { "center": { "x": -294, "y": -994.31, "z": -1114.5 }, "size": { "x": 1.5, "y": 0.12, "z": 1.5 } },
    { "center": { "x": -292.5, "y": -994.31, "z": -1117.5 }, "size": { "x": 1.5, "y": 0.12, "z": 1.5 } },
    { "center": { "x": -292.5, "y": -994.31, "z": -1116 }, "size": { "x": 1.5, "y": 0.12, "z": 1.5 } },
    { "center": { "x": -292.5, "y": -994.31, "z": -1114.5 }, "size": { "x": 1.5, "y": 0.12, "z": 1.5 } },
    { "center": { "x": -291, "y": -994.31, "z": -1117.5 }, "size": { "x": 1.5, "y": 0.12, "z": 1.5 } },
    { "center": { "x": -291, "y": -994.31, "z": -1116 }, "size": { "x": 1.5, "y": 0.12, "z": 1.5 } },
    { "center": { "x": -291, "y": -994.31, "z": -1114.5 }, "size": { "x": 1.5, "y": 0.12, "z": 1.5 } },
    { "center": { "x": -289.5, "y": -994.31, "z": -1117.5 }, "size": { "x": 1.5, "y": 0.12, "z": 1.5 } },
    { "center": { "x": -289.5, "y": -994.31, "z": -1116 }, "size": { "x": 1.5, "y": 0.12, "z": 1.5 } },
    { "center": { "x": -289.5, "y": -994.31, "z": -1114.5 }, "size": { "x": 1.5, "y": 0.12, "z": 1.5 } },
    { "center": { "x": -288, "y": -994.31, "z": -1117.5 }, "size": { "x": 1.5, "y": 0.12, "z": 1.5 } },
    { "center": { "x": -288, "y": -994.31, "z": -1116 }, "size": { "x": 1.5, "y": 0.12, "z": 1.5 } },
    { "center": { "x": -288, "y": -994.31, "z": -1114.5 }, "size": { "x": 1.5, "y": 0.12, "z": 1.5 } },
    { "center": { "x": -286.5, "y": -994.31, "z": -1117.5 }, "size": { "x": 1.5, "y": 0.12, "z": 1.5 } },
    { "center": { "x": -286.5, "y": -994.31, "z": -1116 }, "size": { "x": 1.5, "y": 0.12, "z": 1.5 } },
    { "center": { "x": -286.5, "y": -994.31, "z": -1114.5 }, "size": { "x": 1.5, "y": 0.12, "z": 1.5 } },
    { "center": { "x": -285, "y": -994.31, "z": -1117.5 }, "size": { "x": 1.5, "y": 0.12, "z": 1.5 } },
    { "center": { "x": -285, "y": -994.31, "z": -1116 }, "size": { "x": 1.5, "y": 0.12, "z": 1.5 } },
    { "center": { "x": -285, "y": -994.31, "z": -1114.5 }, "size": { "x": 1.5, "y": 0.12, "z": 1.5 } }
  ]
}
